fortresstools/__init__.py
fortresstools/app/ft.py
fortresstools/command/__init__.py
fortresstools/command/base.py
fortresstools/command/cmake.py
fortresstools/command/dir.py
fortresstools/command/git.py
fortresstools/command/pip.py
fortresstools/command/rsync.py
fortresstools/command/svn.py
fortresstools/command/test.py
fortresstools/command/venv.py
fortresstools/commander/__init__.py
fortresstools/commander/base.py
fortresstools/executor/__init__.py
fortresstools/executor/base.py
fortresstools/executor/shell.py
fortresstools/executor/ssh.py
fortresstools/executor/venv.py
fortresstools/runner/__init__.py
fortresstools/runner/base.py
fortresstools/scripts/__init__.py
fortresstools/scripts/cpp.yaml
fortresstools/scripts/scripts.py
fortresstools/scripts/stm32.yaml
fortresstools/utils/__init__.py
fortresstools/utils/console.py
fortresstools/utils/logger.py
fortresstools/utils/settings.py
FortressTools-3.1.0.dist-info/LICENSE
FortressTools-3.1.0.dist-info/METADATA
FortressTools-3.1.0.dist-info/WHEEL
FortressTools-3.1.0.dist-info/entry_points.txt
FortressTools-3.1.0.dist-info/top_level.txt
FortressTools-3.1.0.dist-info/RECORD
