Metadata-Version: 2.1
Name: FortressTools
Version: 3.1.0
Summary: Personal Tools for development
Home-page: https://github.com/gembcior/FortressTools.git
Author: Gembcior
Author-email: gembcior@gmail.com
License: MIT
Platform: UNKNOWN
Classifier: License :: OSI Approved :: MIT License
Classifier: Operating System :: Unix
Classifier: Operating System :: POSIX
Classifier: Programming Language :: Python :: 3
Classifier: Programming Language :: Python :: 3.6
Classifier: Programming Language :: Python :: 3.7
Classifier: Programming Language :: Python :: 3.8
Requires-Python: >=3.6
License-File: LICENSE
Requires-Dist: pyyaml
Requires-Dist: rich
Requires-Dist: paramiko
